fao56/__init__.py
fao56/chap2.py
fao56/chap3.py
fao56/chap4.py
fao56/clean.py
fao56/version.py
fao56-1.2.0.dist-info/AUTHORS.rst
fao56-1.2.0.dist-info/LICENSE
fao56-1.2.0.dist-info/METADATA
fao56-1.2.0.dist-info/WHEEL
fao56-1.2.0.dist-info/top_level.txt
fao56-1.2.0.dist-info/RECORD
